radiant_mlhub/__init__.py
radiant_mlhub/__version__.py
radiant_mlhub/cli.py
radiant_mlhub/exceptions.py
radiant_mlhub/if_exists.py
radiant_mlhub/py.typed
radiant_mlhub/retry_config.py
radiant_mlhub/session.py
radiant_mlhub/client/__init__.py
radiant_mlhub/client/catalog_downloader.py
radiant_mlhub/client/collections.py
radiant_mlhub/client/datasets.py
radiant_mlhub/client/datetime_utils.py
radiant_mlhub/client/ml_models.py
radiant_mlhub/client/resumable_downloader.py
radiant_mlhub/models/__init__.py
radiant_mlhub/models/collection.py
radiant_mlhub/models/dataset.py
radiant_mlhub/models/ml_model.py
test/__init__.py
test/conftest.py
test/test_cli.py
test/test_client.py
test/test_session.py
test/models/__init__.py
test/models/test_collection.py
test/models/test_dataset.py
test/models/test_ml_model.py
radiant_mlhub-0.5.5.dist-info/LICENSE
radiant_mlhub-0.5.5.dist-info/METADATA
radiant_mlhub-0.5.5.dist-info/WHEEL
radiant_mlhub-0.5.5.dist-info/entry_points.txt
radiant_mlhub-0.5.5.dist-info/top_level.txt
radiant_mlhub-0.5.5.dist-info/RECORD
