Metadata-Version: 2.1
Name: radiant-mlhub
Version: 0.5.5
Summary: A Python client for Radiant MLHub
Home-page: https://github.com/radiantearth/radiant-mlhub
Author: Radiant Earth Foundation
Author-email: devops@radiant.earth
License: Apache License 2.0
Project-URL: Documentation, https://radiant-mlhub.readthedocs.io/
Project-URL: Issue Tracker, https://github.com/radiantearth/radiant-mlhub/issues
Project-URL: Radiant MLHub, https://mlhub.earth
Platform: Platform Independent
Classifier: Programming Language :: Python
Classifier: Programming Language :: Python :: 3
Classifier: Programming Language :: Python :: 3.8
Classifier: Programming Language :: Python :: 3.9
Classifier: Programming Language :: Python :: 3.10
Classifier: Operating System :: OS Independent
Classifier: Natural Language :: English
Classifier: Development Status :: 4 - Beta
Classifier: Intended Audience :: Developers
Classifier: License :: OSI Approved :: Apache Software License
Classifier: Topic :: Scientific/Engineering :: Artificial Intelligence
Classifier: Topic :: Scientific/Engineering :: GIS
Classifier: Topic :: Software Development :: Libraries
Classifier: Topic :: Software Development :: Libraries :: Python Modules
Requires-Python: >=3.8
License-File: LICENSE
Requires-Dist: click (<9.0.0,>=7.1.2)
Requires-Dist: pydantic (~=1.9.2)
Requires-Dist: pystac (~=1.4.0)
Requires-Dist: python-dateutil (~=2.8.2)
Requires-Dist: requests (~=2.27.0)
Requires-Dist: shapely (~=1.8.0)
Requires-Dist: tqdm (~=4.64.0)
Requires-Dist: urllib3 (~=1.26.11)
